{
  "ok": true,
  "build_ok": true,
  "test_ok": true,
  "rounds_executed": 1,
  "attempts": [
    {
      "round": 0,
      "commands": [
        {
          "command": "cargo build",
          "returncode": 0,
          "stdout_tail": [],
          "stderr_tail": [
            "Compiling flashdb_rust v0.1.0 (E:\\009workspace\\codex\\loopforge-contest-driver\\flashDB_rust)",
            "    Finished `dev` profile [unoptimized + debuginfo] target(s) in 0.61s"
          ],
          "ok": true,
          "error": ""
        },
        {
          "command": "cargo test",
          "returncode": 0,
          "stdout_tail": [
            "running 0 tests",
            "",
            "test result: ok. 0 passed; 0 failed; 0 ignored; 0 measured; 0 filtered out; finished in 0.00s",
            "",
            "",
            "running 3 tests",
            "test deleting_a_key_removes_it_from_the_store ... ok",
            "test replacing_a_key_returns_the_previous_value ... ok",
            "test stores_and_reads_values ... ok",
            "",
            "test result: ok. 3 passed; 0 failed; 0 ignored; 0 measured; 0 filtered out; finished in 0.00s",
            "",
            "",
            "running 0 tests",
            "",
            "test result: ok. 0 passed; 0 failed; 0 ignored; 0 measured; 0 filtered out; finished in 0.00s"
          ],
          "stderr_tail": [
            "Compiling flashdb_rust v0.1.0 (E:\\009workspace\\codex\\loopforge-contest-driver\\flashDB_rust)",
            "    Finished `test` profile [unoptimized + debuginfo] target(s) in 0.50s",
            "     Running unittests src\\lib.rs (target\\debug\\deps\\flashdb_rust-bbd0a51323736fe7.exe)",
            "     Running tests\\flashdb_semantics.rs (target\\debug\\deps\\flashdb_semantics-cd5109fe428454d4.exe)",
            "   Doc-tests flashdb_rust"
          ],
          "ok": true,
          "error": ""
        }
      ],
      "repair_action": null,
      "repair_task_packet": null
    }
  ]
}
